README.txt
setup.cfg
setup.py
Products/__init__.py
Products.SquareListing.egg-info/PKG-INFO
Products.SquareListing.egg-info/SOURCES.txt
Products.SquareListing.egg-info/dependency_links.txt
Products.SquareListing.egg-info/entry_points.txt
Products.SquareListing.egg-info/namespace_packages.txt
Products.SquareListing.egg-info/not-zip-safe
Products.SquareListing.egg-info/paster_plugins.txt
Products.SquareListing.egg-info/requires.txt
Products.SquareListing.egg-info/top_level.txt
Products/SquareListing/__init__.py
Products/SquareListing/configure.zcml
Products/SquareListing/interfaces.py
Products/SquareListing/square_listing.pt
Products/SquareListing/view.py
Products/SquareListing/profiles/default/browserlayer.xml
Products/SquareListing/profiles/default/metadata.xml
Products/SquareListing/profiles/default/skins.xml
Products/SquareListing/profiles/default/types.xml
Products/SquareListing/profiles/default/types/Folder.xml
Products/SquareListing/profiles/default/types/Topic.xml
Products/SquareListing/skins/square_listing_resources/bg-style.gif
Products/SquareListing/skins/square_listing_resources/square_listing.css.dtml
docs/HISTORY.txt
docs/INSTALL.txt
docs/LICENSE.GPL
docs/LICENSE.txt