Metadata-Version: 1.0
Name: Products.SquareListing
Version: 0.1.4
Summary: A square listing template for folderish contents
Home-page: htttp://www.abstract.it
Author: Luca Pisani
Author-email: luca.pisani@abstract.it
License: GPL
Keywords: Plone Abstract browser vieww square listing
Platform: UNKNOWN
Classifier: Programming Language :: Python
